prawn/__init__.py
prawn/__main__.py
prawn/stream.py
prawn/version.py
prawn-0.2.1.dist-info/METADATA
prawn-0.2.1.dist-info/WHEEL
prawn-0.2.1.dist-info/top_level.txt
prawn-0.2.1.dist-info/RECORD
